simulateur_trafic/__init__.py
simulateur_trafic/cli.py
simulateur_trafic/core/__init__.py
simulateur_trafic/core/analyseur/__init__.py
simulateur_trafic/core/analyseur/analyseur.py
simulateur_trafic/core/exceptions.py
simulateur_trafic/core/optimisation/__init__.py
simulateur_trafic/core/optimisation/cython_ext/__init__.py
simulateur_trafic/core/optimisation/cython_ext/_position_update.c
simulateur_trafic/core/optimisation/cython_ext/_position_update.cpython-310-x86_64-linux-gnu.so
simulateur_trafic/core/optimisation/cython_ext/_position_update.pyx
simulateur_trafic/core/optimisation/cython_ext/setup.py
simulateur_trafic/core/optimisation/numba_accelerateurs.py
simulateur_trafic/core/simulateur/__init__.py
simulateur_trafic/core/simulateur/simulateur.py
simulateur_trafic/data/config_reseau.json
simulateur_trafic/interface/__init__.py
simulateur_trafic/interface/affichage/__init__.py
simulateur_trafic/interface/affichage/affichage.py
simulateur_trafic/interface/export/__init__.py
simulateur_trafic/interface/export/export.py
simulateur_trafic/models/__init__.py
simulateur_trafic/models/reseau/__init__.py
simulateur_trafic/models/reseau/reseau.py
simulateur_trafic/models/route/__init__.py
simulateur_trafic/models/route/feu_rouge.py
simulateur_trafic/models/route/route.py
simulateur_trafic/models/vehicule/__init__.py
simulateur_trafic/models/vehicule/vehicule.py
simulateur_trafic-0.2.1.dist-info/METADATA
simulateur_trafic-0.2.1.dist-info/WHEEL
simulateur_trafic-0.2.1.dist-info/RECORD
