Metadata-Version: 2.4
Name: simulateur-trafic
Version: 0.2.1
Summary: Similateur de Traffic de Voitures
License: MIT
Keywords: traffic,simulation
Author: Dhia Ben Hamouda
Requires-Python: >=3.10,<3.14
Classifier: License :: OSI Approved :: MIT License
Classifier: Programming Language :: Python :: 3
Classifier: Programming Language :: Python :: 3.10
Classifier: Programming Language :: Python :: 3.11
Classifier: Programming Language :: Python :: 3.12
Classifier: Programming Language :: Python :: 3.13
Requires-Dist: pytest (>=9.0.1,<10.0.0)
Requires-Dist: twine (>=6.2.0,<7.0.0)
